{"apiVersion":"apps/v1","kind":"Deployment","metadata":{"annotations":{"deployment.kubernetes.io/revision":"57","kubectl.kubernetes.io/last-applied-configuration":"{\"apiVersion\":\"apps/v1\",\"kind\":\"Deployment\",\"metadata\":{\"annotations\":{\"timestamp\":\"20211220T170311\"},\"labels\":{\"app\":\"app-feed-service-staging-main\"},\"name\":\"app-feed-service-staging-main\",\"namespace\":\"staging\"},\"spec\":{\"minReadySeconds\":0,\"progressDeadlineSeconds\":600,\"replicas\":1,\"revisionHistoryLimit\":10,\"selector\":{\"matchLabels\":{\"app\":\"app-feed-service-staging-main\"}},\"strategy\":{\"rollingUpdate\":{\"maxSurge\":\"25%\",\"maxUnavailable\":\"25%\"},\"type\":\"RollingUpdate\"},\"template\":{\"metadata\":{\"labels\":{\"app\":\"app-feed-service-staging-main\"}},\"spec\":{\"affinity\":{},\"containers\":[{\"env\":[{\"name\":\"spring.profiles.active\",\"value\":\"dev\"},{\"name\":\"spring.cloud.config.server.git.search-paths\",\"value\":\"staging\"},{\"name\":\"spring.cloud.config.uri\",\"value\":\"http://configservice-staging-main:8012\"},{\"name\":\"eureka.instance.preferIpAddress\",\"value\":\"true\"},{\"name\":\"ELASTIC_APM_SERVICE_NAME\",\"value\":\"app-feed-service-staging\"},{\"name\":\"ELASTIC_APM_SERVER_URLS\",\"value\":\"http://apm-server.logging:8200\"},{\"name\":\"ELASTIC_APM_ENVIRONMENT\",\"value\":\"staging\"}],\"image\":\"nexuscli.adda247.com/app-feed-service/staging/main:66-20211220T1657-releasecp-1.7\",\"imagePullPolicy\":\"Always\",\"name\":\"app-feed-service-staging-main\",\"ports\":[{\"containerPort\":8111,\"name\":\"http\",\"protocol\":\"TCP\"}],\"resources\":{\"limits\":{\"cpu\":\"500m\",\"memory\":\"1024Mi\"},\"requests\":{\"cpu\":\"500m\",\"memory\":\"1024Mi\"}},\"volumeMounts\":null}],\"imagePullSecrets\":[{\"name\":\"staging-regcred\"}],\"nodeSelector\":{},\"terminationGracePeriodSeconds\":30,\"tolerations\":[],\"volumes\":null}}}}\n","timestamp":"20211220T170311"},"creationTimestamp":"2021-08-23T13:14:50Z","generation":330,"labels":{"app":"app-feed-service-staging-main"},"name":"app-feed-service-staging-main","namespace":"staging","resourceVersion":"237596515","selfLink":"/apis/apps/v1/namespaces/staging/deployments/app-feed-service-staging-main","uid":"c31e7ccc-7cdd-4810-a97b-2ae2d2c4e223"},"spec":{"progressDeadlineSeconds":600,"replicas":2,"revisionHistoryLimit":10,"selector":{"matchLabels":{"app":"app-feed-service-staging-main"}},"strategy":{"rollingUpdate":{"maxSurge":"25%","maxUnavailable":"25%"},"type":"RollingUpdate"},"template":{"metadata":{"annotations":{"kubectl.kubernetes.io/restartedAt":"2021-12-19T12:28:17Z"},"creationTimestamp":null,"labels":{"app":"app-feed-service-staging-main"}},"spec":{"affinity":{},"containers":[{"env":[{"name":"spring.profiles.active","value":"dev"},{"name":"spring.cloud.config.server.git.search-paths","value":"staging"},{"name":"spring.cloud.config.uri","value":"http://configservice-staging-main:8012"},{"name":"eureka.instance.preferIpAddress","value":"true"},{"name":"ELASTIC_APM_SERVICE_NAME","value":"app-feed-service-staging"},{"name":"ELASTIC_APM_SERVER_URLS","value":"http://apm-server.logging:8200"},{"name":"ELASTIC_APM_ENVIRONMENT","value":"staging"}],"image":"nexuscli.adda247.com/app-feed-service/staging/main:66-20211220T1657-releasecp-1.7","imagePullPolicy":"Always","name":"app-feed-service-staging-main","ports":[{"containerPort":8111,"name":"http","protocol":"TCP"}],"resources":{"limits":{"cpu":"500m","memory":"1Gi"},"requests":{"cpu":"500m","memory":"1Gi"}},"terminationMessagePath":"/dev/termination-log","terminationMessagePolicy":"File"}],"dnsPolicy":"ClusterFirst","imagePullSecrets":[{"name":"staging-regcred"}],"restartPolicy":"Always","schedulerName":"default-scheduler","securityContext":{},"terminationGracePeriodSeconds":30}}},"status":{"availableReplicas":2,"conditions":[{"lastTransitionTime":"2021-09-01T15:32:26Z","lastUpdateTime":"2021-12-20T11:33:21Z","message":"ReplicaSet \"app-feed-service-staging-main-c4d56d47d\" has successfully progressed.","reason":"NewReplicaSetAvailable","status":"True","type":"Progressing"},{"lastTransitionTime":"2021-12-20T12:24:14Z","lastUpdateTime":"2021-12-20T12:24:14Z","message":"Deployment has minimum availability.","reason":"MinimumReplicasAvailable","status":"True","type":"Available"}],"observedGeneration":330,"readyReplicas":2,"replicas":2,"updatedReplicas":2}}